keygen_api/__init__.py
keygen_api/main.py
keygen.api-0.1.1.dist-info/entry_points.txt
keygen.api-0.1.1.dist-info/WHEEL
keygen.api-0.1.1.dist-info/METADATA
keygen.api-0.1.1.dist-info/RECORD
